rq/__init__.py
rq/command.py
rq/connections.py
rq/decorators.py
rq/defaults.py
rq/dependency.py
rq/exceptions.py
rq/executions.py
rq/group.py
rq/intermediate_queue.py
rq/job.py
rq/local.py
rq/logutils.py
rq/maintenance.py
rq/py.typed
rq/queue.py
rq/registry.py
rq/repeat.py
rq/results.py
rq/scheduler.py
rq/serializers.py
rq/suspension.py
rq/timeouts.py
rq/types.py
rq/utils.py
rq/version.py
rq/worker.py
rq/worker_pool.py
rq/worker_registration.py
rq/cli/__init__.py
rq/cli/__main__.py
rq/cli/cli.py
rq/cli/helpers.py
rq/contrib/__init__.py
rq-2.3.1.dist-info/METADATA
rq-2.3.1.dist-info/WHEEL
rq-2.3.1.dist-info/entry_points.txt
rq-2.3.1.dist-info/licenses/LICENSE
rq-2.3.1.dist-info/RECORD
