Metadata-Version: 2.1
Name: rq
Version: 2.3.1
Summary: RQ is a simple, lightweight, library for creating background jobs, and processing them.
Project-URL: changelog, https://github.com/rq/rq/blob/master/CHANGES.md
Project-URL: documentation, https://python-rq.org/docs/
Project-URL: homepage, https://python-rq.org/
Project-URL: repository, https://github.com/rq/rq/
Author-email: Selwin Ong <selwin.ong@gmail.com>, Vincent Driessen <vincent@3rdcloud.com>
Maintainer: Selwin Ong
License-Expression: BSD-2-Clause
License-File: LICENSE
Classifier: Development Status :: 5 - Production/Stable
Classifier: Intended Audience :: Developers
Classifier: Intended Audience :: End Users/Desktop
Classifier: Intended Audience :: Information Technology
Classifier: Intended Audience :: Science/Research
Classifier: Intended Audience :: System Administrators
Classifier: License :: OSI Approved :: BSD License
Classifier: Operating System :: MacOS
Classifier: Operating System :: POSIX
Classifier: Operating System :: Unix
Classifier: Programming Language :: Python
Classifier: Programming Language :: Python :: 3 :: Only
Classifier: Programming Language :: Python :: 3.8
Classifier: Programming Language :: Python :: 3.9
Classifier: Programming Language :: Python :: 3.10
Classifier: Programming Language :: Python :: 3.11
Classifier: Programming Language :: Python :: 3.12
Classifier: Programming Language :: Python :: 3.13
Classifier: Topic :: Internet
Classifier: Topic :: Scientific/Engineering
Classifier: Topic :: Software Development :: Libraries :: Python Modules
Classifier: Topic :: System :: Distributed Computing
Classifier: Topic :: System :: Monitoring
Classifier: Topic :: System :: Systems Administration
Requires-Python: >=3.8
Requires-Dist: click>=5
Requires-Dist: redis>=3.5
